{"coordinateLong": "-71.4032", "location": "Brown University", "yacks": [{"messageID": "R/548e271d54624a594dd6225e47935", "time": "2014-12-14 19:11:09", "likes": "49", "message": "I like to play jenga on the first date so she knows my pull out game is strong "}, {"messageID": "R/548e33acf1caab2cb2d17e3d0ad44", "time": "2014-12-14 20:04:44", "likes": "15", "message": "Finals Advice: YOU IS KIND. YOU IS SMART. YOU IS IMPORTANT."}, {"messageID": "R/548e23cdac747210a5888d17ed429", "time": "2014-12-14 18:57:01", "likes": "15", "message": "An hour of my life is worth $8.25."}, {"messageID": "R/548e332bd5dd9ec4d2882530b6790", "time": "2014-12-14 20:02:35", "likes": "14", "message": "Remember that however badly you fail your finals someone from your hometown is still trying to be a rapper "}, {"messageID": "R/548e2f6eab6d8872459c0f12df681", "time": "2014-12-14 19:46:38", "likes": "10", "message": "I was so enchanted by your beauty that I ran into that wall over there. So I'm going to need your name and number for insurance purposes. "}, {"messageID": "R/548e23ef17b5a60da7bd3474d89d4", "time": "2014-12-14 18:57:35", "likes": "10", "message": "Gyms need punching bags. I could go fucking HAM right now I'm so pissed for no reason"}, {"messageID": "R/548e2588d62c4921faae4c7043a2f", "time": "2014-12-14 19:04:24", "likes": "9", "message": "The best servers are people that do drugs...they are so much happier"}, {"messageID": "R/548e311b56f393948a4ab12ee0ee0", "time": "2014-12-14 19:53:47", "likes": "8", "message": "I want to have a college experience with a girl #lesbehonest "}, {"messageID": "R/548e302de284b713abd8e4439273c", "time": "2014-12-14 19:49:49", "likes": "8", "message": "When you're relationship becomes a full time job -.-"}, {"messageID": "R/548e38e038f199074d981bb69ca51", "time": "2014-12-14 20:26:56", "likes": "6", "message": "Feeding your snail is something not to do at a stop light "}, {"messageID": "R/548e26b2e6cc7f4e466089a8bc9fe", "time": "2014-12-14 19:09:22", "likes": "6", "message": "I banged a girl in her ass last night and when I pulled out she shit everywhere...weird night "}, {"messageID": "R/548e258360f060a8d312220fdbd58", "time": "2014-12-14 19:04:19", "likes": "6", "message": "I always feel so creepy when I'm walking behind people at night but then I remember I'm just a squirrel"}, {"messageID": "R/548e2b109843f286a9928238c537a", "time": "2014-12-14 19:28:00", "likes": "5", "message": "stopping by providence, I'd be remiss if i didn't leave a yak.  you have a great town!"}, {"messageID": "R/548e253d76be1df43856a64b8cd49", "time": "2014-12-14 19:03:09", "likes": "5", "message": "I wrote spongebob quotes on the tops of the pages of my math exam in the hopes that cultural references = extra credit"}, {"messageID": "R/548e333d569666652f121303c57f3", "time": "2014-12-14 20:02:53", "likes": "4", "message": "I just want to go home. "}, {"messageID": "R/548e32746b3a9a1fa1f7a39210cb7", "time": "2014-12-14 19:59:32", "likes": "4", "message": "I wish I had a girl that played fantasy football"}, {"messageID": "R/548e2aae7081d91af0ac4e38e3aec", "time": "2014-12-14 19:26:22", "likes": "4", "message": "I really miss you but I am afraid of I will bother you"}, {"messageID": "R/548e288ef0ac9cb0f8af0049926bc", "time": "2014-12-14 19:17:18", "likes": "4", "message": "I wipe my own ass! I wipe my own ass! "}, {"messageID": "R/548e267e289c7393e709598831bcf", "time": "2014-12-14 19:08:30", "likes": "4", "message": "That moment when all you want is a drink but you're not 21 yet and you can't find anyone to buy some for you. "}, {"messageID": "R/548e37c2864202cf9cf1997ecc430", "time": "2014-12-14 20:22:10", "likes": "3", "message": "what channel is Cartoon Network? "}, {"messageID": "R/548e376627eec9429b1960167b168", "time": "2014-12-14 20:20:38", "likes": "3", "message": "I want to hook up with a chick but I'm a straight girl 😁😁"}, {"messageID": "R/548e34a75011c3e962d13ad3de46c", "time": "2014-12-14 20:08:55", "likes": "3", "message": "Hangovers make me pissed the fuck off at the whole world..anyone else?"}, {"messageID": "R/548e25124d9dbbbe45039cf0b187e", "time": "2014-12-14 19:02:26", "likes": "3", "message": "And i'm rollin weed  you know it's fucking up the ozoooone"}, {"messageID": "R/548e3a1862dcb83fef36854c8e856", "time": "2014-12-14 20:32:08", "likes": "2", "message": "Looks like my family is not going on that road trip to FL for Xmas/New Years Eve anymore, having the whole house to myself for an entire week was too good to be true   😢😢😢😢😢😢"}, {"messageID": "R/548e38c0e944c419493552184b1ab", "time": "2014-12-14 20:26:24", "likes": "2", "message": "Wearing a Lebron jersey to my final tomorrow since I don't plan on passing "}, {"messageID": "R/548e37faef600584cbbc7b9d71f54", "time": "2014-12-14 20:23:06", "likes": "2", "message": "Never eat seafood in snowden. "}, {"messageID": "R/548e2b9be8004618a7736173f5cfc", "time": "2014-12-14 19:30:19", "likes": "2", "message": "If the first few texts ain't right then you know its never going to work. ✌️"}, {"messageID": "R/548e2b4a15cefc07a6c4c999b61e9", "time": "2014-12-14 19:28:58", "likes": "2", "message": "I need a blowjob so bad"}, {"messageID": "R/548e3cbe1eb08fc3605ffc04b3706", "time": "2014-12-14 20:43:26", "likes": "1", "message": "Is there anyone normal at Brown?! Jeez, is everyone this awkward?"}, {"messageID": "R/548e3bfae65507b55a69223b505a3", "time": "2014-12-14 20:40:10", "likes": "1", "message": "I can't wait till the cowboys rail the eagles tonight"}, {"messageID": "R/548e3819496214ad4da5a488905a6", "time": "2014-12-14 20:23:37", "likes": "1", "message": "All I need in life right now is a stoner chick FWB"}, {"messageID": "R/548e347fa401db300eb434d14910e", "time": "2014-12-14 20:08:15", "likes": "1", "message": "Two hours of hell left "}, {"messageID": "R/548e2cc57cd11d616d7126e661bd6", "time": "2014-12-14 19:35:17", "likes": "1", "message": "Any hot guys in the cove "}, {"messageID": "R/548e3cf9920420a3bbe84fb074f78", "time": "2014-12-14 20:44:25", "likes": "0", "message": "I have this new weird thing called feelings so when you do some fucked up shit to me, the immediate reaction is it hurts them and it makes it harder for me to like u everytime u do."}, {"messageID": "R/548e3cdb9cb49dc9833d0db3d7089", "time": "2014-12-14 20:43:55", "likes": "0", "message": "Word up for day nines 🙌"}, {"messageID": "R/548e3cb04739d0294fd2848e1eb59", "time": "2014-12-14 20:43:12", "likes": "0", "message": "When you miss that one person you know you shouldn't 😞"}, {"messageID": "R/548e39c5822ae9d1bc75a995e5cba", "time": "2014-12-14 20:30:45", "likes": "0", "message": "J ride to jwuuu"}, {"messageID": "R/548e382e862f21b8680d614f1a0e0", "time": "2014-12-14 20:23:58", "likes": "0", "message": "Don't be impossible to get.."}, {"messageID": "R/548e365683d17526a59163f06875f", "time": "2014-12-14 20:16:06", "likes": "0", "message": "I'm a senior and I have yet to have a fwb with a girl. "}, {"messageID": "R/548e30d4c8429f6126fb9017ba9c8", "time": "2014-12-14 19:52:36", "likes": "0", "message": "I'd love it if a girl came and cuddled right now "}, {"messageID": "R/548e2c53b84562be637ee0fe083e2", "time": "2014-12-14 19:33:23", "likes": "0", "message": "I hate having a full laundry basket."}, {"messageID": "R/548e3c380ee91b350fa642d9f1157", "time": "2014-12-14 20:41:12", "likes": "-1", "message": "I have the biggest crush on this guy that works at Hollister😍 he looks like a disney prince and I want him so bad!!! He's such a sweetheart but he like someone else😭"}, {"messageID": "R/548e398f5f49ec7b2fc1d16711845", "time": "2014-12-14 20:29:51", "likes": "-1", "message": "Can't wait to see if I get a bid tomorrow 😁 #sororitylyphe"}, {"messageID": "R/548e39550ac85a2222837b7252f7d", "time": "2014-12-14 20:28:53", "likes": "-2", "message": "Two reasons I'm excited it is Monday tomorrow is 1. One day closer to break and 2. I get to see the bae tomorrow so bring on Monday! "}, {"messageID": "R/548e3132ec424b2d1731bf28a28c9", "time": "2014-12-14 19:54:10", "likes": "-2", "message": "I need a dime "}], "time": "20:45:50.603562", "coordinateLat": "41.8262"}