{"coordinateLong": "-118.243685", "location": "Los Angeles, CA", "yacks": [{"messageID": "R/548e40d70b30c263a88c33a2014dc", "time": "2014-12-14 21:00:55", "likes": "5", "message": "Jesus take the scantron "}, {"messageID": "R/548e4ce8a3c10c274d48a38e12cc5", "time": "2014-12-14 21:52:24", "likes": "3", "message": "I want to eat Oreos but I have no milk. The fuck is life. "}, {"messageID": "R/548e4b56538fd95f54a4bb017b752", "time": "2014-12-14 21:45:42", "likes": "1", "message": "Yak game here weaker than the economy. "}, {"messageID": "R/548e4a274e30d7bb290d7a82d48a1", "time": "2014-12-14 21:40:39", "likes": "1", "message": "Have you ever came so hard that a little tear slips out?"}, {"messageID": "R/548e4e002122a1ef823cd453f1114", "time": "2014-12-14 21:57:04", "likes": "0", "message": "I got a check in the mail for $16,482.29 wtf do I now?"}, {"messageID": "R/548e4d69a2730e8eeec08e6a53799", "time": "2014-12-14 21:54:33", "likes": "0", "message": "Yik yak telling me to slow my roll. Bitch please✋"}, {"messageID": "R/548e4c22531e6c1e2338bc2cad72d", "time": "2014-12-14 21:49:06", "likes": "0", "message": "It's amazing how mean some people can be even when they don't know who they're talking to. "}, {"messageID": "R/548e4896bd8a9d1f6a25e9352967b", "time": "2014-12-14 21:33:58", "likes": "0", "message": "Grams for 10$ 😍"}, {"messageID": "R/548e486a695aef96c13b4e015655b", "time": "2014-12-14 21:33:14", "likes": "0", "message": "Anyone know what their shooting on kchung rd? "}, {"messageID": "R/548e42c90de89fbcd721ef9c0e1a6", "time": "2014-12-14 21:09:13", "likes": "-3", "message": "Dtla yik yak game soft"}], "time": "22:13:22.014250", "coordinateLat": "34.052234"}